cdplogger_client/__init__.py
cdplogger_client/cdplogger.py
cdplogger_client/container_pb2.py
cdplogger_client/database_pb2.py
cdplogger_client/variant_pb2.py
cdplogger_client/test/__init__.py
cdplogger_client/test/fake_data.py
cdplogger_client/test/test_client.py
cdplogger_client/test/test_main.py
cdplogger_client-1.0.2.dist-info/licenses/LICENSE.txt
cdplogger_client-1.0.2.dist-info/METADATA
cdplogger_client-1.0.2.dist-info/WHEEL
cdplogger_client-1.0.2.dist-info/top_level.txt
cdplogger_client-1.0.2.dist-info/RECORD
