Metadata-Version: 2.4
Name: cdplogger-client
Version: 1.0.2
Summary: Provides an API that allows to interact with CDP to access logger data
Home-page: 
Author: CDP Technologies AS
Author-email: info@cdptech.com
License: MIT
Keywords: cdp cdpstudio studio client cdp-client cdp_client cdp_logger cdp-logger cdplogger_client cdp_logger_client cdp-logger-client logger
Classifier: Development Status :: 5 - Production/Stable
Classifier: Environment :: Console
Classifier: Intended Audience :: Developers
Classifier: License :: OSI Approved :: MIT License
Classifier: Operating System :: OS Independent
Classifier: Topic :: Software Development
Classifier: Programming Language :: Python :: 2.7
Classifier: Programming Language :: Python :: 3
Classifier: Programming Language :: Python :: 3.3
Classifier: Programming Language :: Python :: 3.4
Classifier: Programming Language :: Python :: 3.5
Classifier: Programming Language :: Python :: 3.6
License-File: LICENSE.txt
Requires-Dist: promise==2.2.1
Requires-Dist: websocket-client==0.56.0
Requires-Dist: protobuf==3.7.1
Requires-Dist: mock==3.0.5
Dynamic: author
Dynamic: author-email
Dynamic: classifier
Dynamic: description
Dynamic: keywords
Dynamic: license
Dynamic: license-file
Dynamic: requires-dist
Dynamic: summary
